structlogzio/__init__.py
structlogzio/_handler.py
logzio_structlog_handler-0.1.1.dist-info/LICENSE
logzio_structlog_handler-0.1.1.dist-info/WHEEL
logzio_structlog_handler-0.1.1.dist-info/METADATA
logzio_structlog_handler-0.1.1.dist-info/RECORD
