Metadata-Version: 2.1
Name: logzio-structlog-handler
Version: 0.1.1
Summary: Package for sending structlog-s to logzio
Home-page: https://github.com/programeri-tech/logzio-structlog-handler
License: MIT
Author: nikooola
Author-email: nikolassmiljanic5@gmail.com
Requires-Python: >=3.8,<4.0
Classifier: License :: OSI Approved :: MIT License
Classifier: Natural Language :: English
Classifier: Programming Language :: Python
Classifier: Programming Language :: Python :: 3
Classifier: Programming Language :: Python :: 3 :: Only
Classifier: Programming Language :: Python :: 3.10
Classifier: Programming Language :: Python :: 3.8
Classifier: Programming Language :: Python :: 3.9
Classifier: Programming Language :: Python :: Implementation :: CPython
Classifier: Topic :: Software Development :: Libraries :: Python Modules
Requires-Dist: logzio-python-handler (==3.0.0)
Project-URL: Repository, https://github.com/programeri-tech/logzio-structlog-handler
